Base.py
tmaridashvilidptsk1-0.1.dist-info/METADATA
tmaridashvilidptsk1-0.1.dist-info/WHEEL
tmaridashvilidptsk1-0.1.dist-info/top_level.txt
tmaridashvilidptsk1-0.1.dist-info/RECORD
