Metadata-Version: 2.1
Name: tmaridashvilidptsk1
Version: 0.1
Summary: dpt1
